granola_py-1.0.6.dist-info/METADATA
granola_py-1.0.6.dist-info/WHEEL
granola_py-1.0.6.dist-info/license_files/LICENSE.md
granola/__init__.py
granola/granola.cpython-311-darwin.so
granola_py-1.0.6.dist-info/RECORD
